b'<?xml version="1.0" encoding="UTF-8"?><data><request><type>LatLon</type><query>Lat 12.43 and Lon 75.74</query></request><weather><date>2018-07-24</date><astronomy><sunrise>06:11 AM</sunrise><sunset>06:55 PM</sunset><moonrise>04:14 PM</moonrise><moonset>03:12 AM</moonset><moon_phase>Waxing Gibbous</moon_phase><moon_illumination>77</moon_illumination></astronomy><maxtempC>23</maxtempC><maxtempF>73</maxtempF><mintempC>21</mintempC><mintempF>70</mintempF><avgtempC>22</avgtempC><avgtempF>71</avgtempF><totalSnow_cm>0.0</totalSnow_cm><sunHour>6.2</sunHour><uvIndex>5</uvIndex><hourly><time>0</time><tempC>21</tempC><tempF>70</tempF><windspeedMiles>5</windspeedMiles><windspeedKmph>8</windspeedKmph><winddirDegree>266</winddirDegree><winddir16Point>W</winddir16Point><weatherCode>353</weatherCode><weatherIconUrl><![CDATA[http://cdn.worldweatheronline.com/images/wsymbols01_png_64/wsymbol_0025_light_rain_showers_night.png]]></weatherIconUrl><weatherDesc><![CDATA[Light rain shower]]></weatherDesc><precipMM>1.5</precipMM><precipInches>0.1</precipInches><humidity>93</humidity><visibility>10</visibility><visibilityMiles>6</visibilityMiles><pressure>1010</pressure><pressureInches>30</pressureInches><cloudcover>82</cloudcover><HeatIndexC>24</HeatIndexC><HeatIndexF>76</HeatIndexF><DewPointC>20</DewPointC><DewPointF>68</DewPointF><WindChillC>21</WindChillC><WindChillF>70</WindChillF><WindGustMiles>7</WindGustMiles><WindGustKmph>12</WindGustKmph><FeelsLikeC>21</FeelsLikeC><FeelsLikeF>70</FeelsLikeF><uvIndex>1</uvIndex></hourly><hourly><time>300</time><tempC>21</tempC><tempF>70</tempF><windspeedMiles>2</windspeedMiles><windspeedKmph>3</windspeedKmph><winddirDegree>243</winddirDegree><winddir16Point>WSW</winddir16Point><weatherCode>119</weatherCode><weatherIconUrl><![CDATA[http://cdn.worldweatheronline.com/images/wsymbols01_png_64/wsymbol_0003_white_cloud.png]]></weatherIconUrl><weatherDesc><![CDATA[Cloudy]]></weatherDesc><precipMM>0.0</precipMM><precipInches>0.0</precipInches><humidity>94</humidity><visibility>10</visibility><visibilityMiles>6</visibilityMiles><pressure>1010</pressure><pressureInches>30</pressureInches><cloudcover>70</cloudcover><HeatIndexC>24</HeatIndexC><HeatIndexF>76</HeatIndexF><DewPointC>21</DewPointC><DewPointF>69</DewPointF><WindChillC>22</WindChillC><WindChillF>71</WindChillF><WindGustMiles>3</WindGustMiles><WindGustKmph>4</WindGustKmph><FeelsLikeC>22</FeelsLikeC><FeelsLikeF>71</FeelsLikeF><uvIndex>1</uvIndex></hourly><hourly><time>600</time><tempC>21</tempC><tempF>70</tempF><windspeedMiles>4</windspeedMiles><windspeedKmph>6</windspeedKmph><winddirDegree>265</winddirDegree><winddir16Point>W</winddir16Point><weatherCode>356</weatherCode><weatherIconUrl><![CDATA[http://cdn.worldweatheronline.com/images/wsymbols01_png_64/wsymbol_0010_heavy_rain_showers.png]]></weatherIconUrl><weatherDesc><![CDATA[Moderate or heavy rain shower]]></weatherDesc><precipMM>3.5</precipMM><precipInches>0.1</precipInches><humidity>95</humidity><visibility>7</visibility><visibilityMiles>4</visibilityMiles><pressure>1011</pressure><pressureInches>30</pressureInches><cloudcover>97</cloudcover><HeatIndexC>24</HeatIndexC><HeatIndexF>76</HeatIndexF><DewPointC>21</DewPointC><DewPointF>69</DewPointF><WindChillC>22</WindChillC><WindChillF>71</WindChillF><WindGustMiles>6</WindGustMiles><WindGustKmph>9</WindGustKmph><FeelsLikeC>22</FeelsLikeC><FeelsLikeF>71</FeelsLikeF><uvIndex>5</uvIndex></hourly><hourly><time>900</time><tempC>23</tempC><tempF>73</tempF><windspeedMiles>5</windspeedMiles><windspeedKmph>8</windspeedKmph><winddirDegree>261</winddirDegree><winddir16Point>W</winddir16Point><weatherCode>122</weatherCode><weatherIconUrl><![CDATA[http://cdn.worldweatheronline.com/images/wsymbols01_png_64/wsymbol_0004_black_low_cloud.png]]></weatherIconUrl><weatherDesc><![CDATA[Overcast]]></weatherDesc><precipMM>0.0</precipMM><precipInches>0.0</precipInches><humidity>92</humidity><visibility>10</visibility><visibilityMiles>6</visibilityMiles><pressure>1012</pressure><pressureInches>30</pressureInches><cloudcover>93</cloudcover><HeatIndexC>25</HeatIndexC><HeatIndexF>77</HeatIndexF><DewPointC>21</DewPointC><DewPointF>70</DewPointF><WindChillC>23</WindChillC><WindChillF>73</WindChillF><WindGustMiles>6</WindGustMiles><WindGustKmph>10</WindGustKmph><FeelsLikeC>25</FeelsLikeC><FeelsLikeF>77</FeelsLikeF><uvIndex>5</uvIndex></hourly><hourly><time>1200</time><tempC>23</tempC><tempF>73</tempF><windspeedMiles>6</windspeedMiles><windspeedKmph>10</windspeedKmph><winddirDegree>271</winddirDegree><winddir16Point>W</winddir16Point><weatherCode>353</weatherCode><weatherIconUrl><![CDATA[http://cdn.worldweatheronline.com/images/wsymbols01_png_64/wsymbol_0009_light_rain_showers.png]]></weatherIconUrl><weatherDesc><![CDATA[Light rain shower]]></weatherDesc><precipMM>2.3</precipMM><precipInches>0.1</precipInches><humidity>90</humidity><visibility>10</visibility><visibilityMiles>6</visibilityMiles><pressure>1011</pressure><pressureInches>30</pressureInches><cloudcover>87</cloudcover><HeatIndexC>25</HeatIndexC><HeatIndexF>77</HeatIndexF><DewPointC>21</DewPointC><DewPointF>70</DewPointF><WindChillC>23</WindChillC><WindChillF>73</WindChillF><WindGustMiles>9</WindGustMiles><WindGustKmph>15</WindGustKmph><FeelsLikeC>25</FeelsLikeC><FeelsLikeF>77</FeelsLikeF><uvIndex>5</uvIndex></hourly><hourly><time>1500</time><tempC>23</tempC><tempF>73</tempF><windspeedMiles>6</windspeedMiles><windspeedKmph>9</windspeedKmph><winddirDegree>267</winddirDegree><winddir16Point>W</winddir16Point><weatherCode>122</weatherCode><weatherIconUrl><![CDATA[http://cdn.worldweatheronline.com/images/wsymbols01_png_64/wsymbol_0004_black_low_cloud.png]]></weatherIconUrl><weatherDesc><![CDATA[Overcast]]></weatherDesc><precipMM>0.0</precipMM><precipInches>0.0</precipInches><humidity>90</humidity><visibility>10</visibility><visibilityMiles>6</visibilityMiles><pressure>1010</pressure><pressureInches>30</pressureInches><cloudcover>98</cloudcover><HeatIndexC>25</HeatIndexC><HeatIndexF>77</HeatIndexF><DewPointC>21</DewPointC><DewPointF>70</DewPointF><WindChillC>23</WindChillC><WindChillF>73</WindChillF><WindGustMiles>8</WindGustMiles><WindGustKmph>12</WindGustKmph><FeelsLikeC>25</FeelsLikeC><FeelsLikeF>77</FeelsLikeF><uvIndex>5</uvIndex></hourly><hourly><time>1800</time><tempC>22</tempC><tempF>71</tempF><windspeedMiles>4</windspeedMiles><windspeedKmph>7</windspeedKmph><winddirDegree>276</winddirDegree><winddir16Point>W</winddir16Point><weatherCode>353</weatherCode><weatherIconUrl><![CDATA[http://cdn.worldweatheronline.com/images/wsymbols01_png_64/wsymbol_0025_light_rain_showers_night.png]]></weatherIconUrl><weatherDesc><![CDATA[Light rain shower]]></weatherDesc><precipMM>1.2</precipMM><precipInches>0.0</precipInches><humidity>93</humidity><visibility>10</visibility><visibilityMiles>6</visibilityMiles><pressure>1012</pressure><pressureInches>30</pressureInches><cloudcover>81</cloudcover><HeatIndexC>24</HeatIndexC><HeatIndexF>76</HeatIndexF><DewPointC>20</DewPointC><DewPointF>69</DewPointF><WindChillC>22</WindChillC><WindChillF>71</WindChillF><WindGustMiles>7</WindGustMiles><WindGustKmph>12</WindGustKmph><FeelsLikeC>22</FeelsLikeC><FeelsLikeF>71</FeelsLikeF><uvIndex>1</uvIndex></hourly><hourly><time>2100</time><tempC>21</tempC><tempF>70</tempF><windspeedMiles>2</windspeedMiles><windspeedKmph>3</windspeedKmph><winddirDegree>248</winddirDegree><winddir16Point>WSW</winddir16Point><weatherCode>119</weatherCode><weatherIconUrl><![CDATA[http://cdn.worldweatheronline.com/images/wsymbols01_png_64/wsymbol_0003_white_cloud.png]]></weatherIconUrl><weatherDesc><![CDATA[Cloudy]]></weatherDesc><precipMM>0.0</precipMM><precipInches>0.0</precipInches><humidity>93</humidity><visibility>10</visibility><visibilityMiles>6</visibilityMiles><pressure>1013</pressure><pressureInches>30</pressureInches><cloudcover>77</cloudcover><HeatIndexC>24</HeatIndexC><HeatIndexF>76</HeatIndexF><DewPointC>20</DewPointC><DewPointF>68</DewPointF><WindChillC>21</WindChillC><WindChillF>70</WindChillF><WindGustMiles>3</WindGustMiles><WindGustKmph>5</WindGustKmph><FeelsLikeC>21</FeelsLikeC><FeelsLikeF>70</FeelsLikeF><uvIndex>1</uvIndex></hourly></weather></data>'