b'<?xml version="1.0" encoding="UTF-8"?><data><request><type>LatLon</type><query>Lat 39.34 and Lon 71.51</query></request><weather><date>2017-04-08</date><astronomy><sunrise>05:48 AM</sunrise><sunset>06:44 PM</sunset><moonrise>03:58 PM</moonrise><moonset>04:23 AM</moonset><moon_phase>Waxing Gibbous</moon_phase><moon_illumination>84</moon_illumination></astronomy><maxtempC>-13</maxtempC><maxtempF>9</maxtempF><mintempC>-24</mintempC><mintempF>-11</mintempF><avgtempC>-17</avgtempC><avgtempF>1</avgtempF><totalSnow_cm>1.9</totalSnow_cm><sunHour>13.0</sunHour><uvIndex>1</uvIndex><hourly><time>0</time><tempC>-21</tempC><tempF>-5</tempF><windspeedMiles>2</windspeedMiles><windspeedKmph>3</windspeedKmph><winddirDegree>252</winddirDegree><winddir16Point>WSW</winddir16Point><weatherCode>335</weatherCode><weatherIconUrl><![CDATA[http://cdn.worldweatheronline.com/images/wsymbols01_png_64/wsymbol_0028_heavy_snow_showers_night.png]]></weatherIconUrl><weatherDesc><![CDATA[Patchy heavy snow]]></weatherDesc><precipMM>0.6</precipMM><precipInches>0.0</precipInches><humidity>97</humidity><visibility>5</visibility><visibilityMiles>3</visibilityMiles><pressure>1025</pressure><pressureInches>31</pressureInches><cloudcover>65</cloudcover><HeatIndexC>-21</HeatIndexC><HeatIndexF>-5</HeatIndexF><DewPointC>-21</DewPointC><DewPointF>-6</DewPointF><WindChillC>-21</WindChillC><WindChillF>-5</WindChillF><WindGustMiles>3</WindGustMiles><WindGustKmph>5</WindGustKmph><FeelsLikeC>-21</FeelsLikeC><FeelsLikeF>-5</FeelsLikeF><uvIndex>1</uvIndex></hourly><hourly><time>300</time><tempC>-21</tempC><tempF>-5</tempF><windspeedMiles>2</windspeedMiles><windspeedKmph>3</windspeedKmph><winddirDegree>226</winddirDegree><winddir16Point>SW</winddir16Point><weatherCode>260</weatherCode><weatherIconUrl><![CDATA[http://cdn.worldweatheronline.com/images/wsymbols01_png_64/wsymbol_0007_fog.png]]></weatherIconUrl><weatherDesc><![CDATA[Freezing fog]]></weatherDesc><precipMM>0.0</precipMM><precipInches>0.0</precipInches><humidity>98</humidity><visibility>0</visibility><visibilityMiles>0</visibilityMiles><pressure>1025</pressure><pressureInches>31</pressureInches><cloudcover>71</cloudcover><HeatIndexC>-21</HeatIndexC><HeatIndexF>-5</HeatIndexF><DewPointC>-21</DewPointC><DewPointF>-6</DewPointF><WindChillC>-23</WindChillC><WindChillF>-10</WindChillF><WindGustMiles>4</WindGustMiles><WindGustKmph>6</WindGustKmph><FeelsLikeC>-23</FeelsLikeC><FeelsLikeF>-10</FeelsLikeF><uvIndex>1</uvIndex></hourly><hourly><time>600</time><tempC>-16</tempC><tempF>2</tempF><windspeedMiles>2</windspeedMiles><windspeedKmph>4</windspeedKmph><winddirDegree>232</winddirDegree><winddir16Point>SW</winddir16Point><weatherCode>335</weatherCode><weatherIconUrl><![CDATA[http://cdn.worldweatheronline.com/images/wsymbols01_png_64/wsymbol_0012_heavy_snow_showers.png]]></weatherIconUrl><weatherDesc><![CDATA[Patchy heavy snow]]></weatherDesc><precipMM>0.6</precipMM><precipInches>0.0</precipInches><humidity>87</humidity><visibility>5</visibility><visibilityMiles>3</visibilityMiles><pressure>1025</pressure><pressureInches>31</pressureInches><cloudcover>55</cloudcover><HeatIndexC>-16</HeatIndexC><HeatIndexF>2</HeatIndexF><DewPointC>-18</DewPointC><DewPointF>-1</DewPointF><WindChillC>-19</WindChillC><WindChillF>-3</WindChillF><WindGustMiles>3</WindGustMiles><WindGustKmph>5</WindGustKmph><FeelsLikeC>-19</FeelsLikeC><FeelsLikeF>-3</FeelsLikeF><uvIndex>1</uvIndex></hourly><hourly><time>900</time><tempC>-14</tempC><tempF>7</tempF><windspeedMiles>5</windspeedMiles><windspeedKmph>8</windspeedKmph><winddirDegree>258</winddirDegree><winddir16Point>WSW</winddir16Point><weatherCode>200</weatherCode><weatherIconUrl><![CDATA[http://cdn.worldweatheronline.com/images/wsymbols01_png_64/wsymbol_0016_thundery_showers.png]]></weatherIconUrl><weatherDesc><![CDATA[Thundery outbreaks possible]]></weatherDesc><precipMM>0.0</precipMM><precipInches>0.0</precipInches><humidity>86</humidity><visibility>9</visibility><visibilityMiles>5</visibilityMiles><pressure>1021</pressure><pressureInches>31</pressureInches><cloudcover>39</cloudcover><HeatIndexC>-14</HeatIndexC><HeatIndexF>7</HeatIndexF><DewPointC>-16</DewPointC><DewPointF>4</DewPointF><WindChillC>-19</WindChillC><WindChillF>-2</WindChillF><WindGustMiles>5</WindGustMiles><WindGustKmph>9</WindGustKmph><FeelsLikeC>-19</FeelsLikeC><FeelsLikeF>-2</FeelsLikeF><uvIndex>1</uvIndex></hourly><hourly><time>1200</time><tempC>-13</tempC><tempF>9</tempF><windspeedMiles>7</windspeedMiles><windspeedKmph>11</windspeedKmph><winddirDegree>275</winddirDegree><winddir16Point>W</winddir16Point><weatherCode>392</weatherCode><weatherIconUrl><![CDATA[http://cdn.worldweatheronline.com/images/wsymbols01_png_64/wsymbol_0016_thundery_showers.png]]></weatherIconUrl><weatherDesc><![CDATA[Patchy light snow with thunder]]></weatherDesc><precipMM>0.0</precipMM><precipInches>0.0</precipInches><humidity>89</humidity><visibility>10</visibility><visibilityMiles>6</visibilityMiles><pressure>1021</pressure><pressureInches>31</pressureInches><cloudcover>57</cloudcover><HeatIndexC>-13</HeatIndexC><HeatIndexF>9</HeatIndexF><DewPointC>-14</DewPointC><DewPointF>6</DewPointF><WindChillC>-19</WindChillC><WindChillF>-2</WindChillF><WindGustMiles>8</WindGustMiles><WindGustKmph>13</WindGustKmph><FeelsLikeC>-19</FeelsLikeC><FeelsLikeF>-2</FeelsLikeF><uvIndex>1</uvIndex></hourly><hourly><time>1500</time><tempC>-14</tempC><tempF>7</tempF><windspeedMiles>6</windspeedMiles><windspeedKmph>10</windspeedKmph><winddirDegree>268</winddirDegree><winddir16Point>W</winddir16Point><weatherCode>200</weatherCode><weatherIconUrl><![CDATA[http://cdn.worldweatheronline.com/images/wsymbols01_png_64/wsymbol_0016_thundery_showers.png]]></weatherIconUrl><weatherDesc><![CDATA[Thundery outbreaks possible]]></weatherDesc><precipMM>0.0</precipMM><precipInches>0.0</precipInches><humidity>91</humidity><visibility>9</visibility><visibilityMiles>5</visibilityMiles><pressure>1022</pressure><pressureInches>31</pressureInches><cloudcover>62</cloudcover><HeatIndexC>-14</HeatIndexC><HeatIndexF>7</HeatIndexF><DewPointC>-15</DewPointC><DewPointF>5</DewPointF><WindChillC>-20</WindChillC><WindChillF>-4</WindChillF><WindGustMiles>7</WindGustMiles><WindGustKmph>12</WindGustKmph><FeelsLikeC>-20</FeelsLikeC><FeelsLikeF>-4</FeelsLikeF><uvIndex>1</uvIndex></hourly><hourly><time>1800</time><tempC>-18</tempC><tempF>0</tempF><windspeedMiles>3</windspeedMiles><windspeedKmph>5</windspeedKmph><winddirDegree>236</winddirDegree><winddir16Point>SW</winddir16Point><weatherCode>335</weatherCode><weatherIconUrl><![CDATA[http://cdn.worldweatheronline.com/images/wsymbols01_png_64/wsymbol_0028_heavy_snow_showers_night.png]]></weatherIconUrl><weatherDesc><![CDATA[Patchy heavy snow]]></weatherDesc><precipMM>1.1</precipMM><precipInches>0.0</precipInches><humidity>95</humidity><visibility>5</visibility><visibilityMiles>3</visibilityMiles><pressure>1026</pressure><pressureInches>31</pressureInches><cloudcover>56</cloudcover><HeatIndexC>-18</HeatIndexC><HeatIndexF>0</HeatIndexF><DewPointC>-18</DewPointC><DewPointF>-1</DewPointF><WindChillC>-22</WindChillC><WindChillF>-7</WindChillF><WindGustMiles>5</WindGustMiles><WindGustKmph>8</WindGustKmph><FeelsLikeC>-22</FeelsLikeC><FeelsLikeF>-7</FeelsLikeF><uvIndex>1</uvIndex></hourly><hourly><time>2100</time><tempC>-24</tempC><tempF>-11</tempF><windspeedMiles>5</windspeedMiles><windspeedKmph>8</windspeedKmph><winddirDegree>192</winddirDegree><winddir16Point>SSW</winddir16Point><weatherCode>143</weatherCode><weatherIconUrl><![CDATA[http://cdn.worldweatheronline.com/images/wsymbols01_png_64/wsymbol_0006_mist.png]]></weatherIconUrl><weatherDesc><![CDATA[Mist]]></weatherDesc><precipMM>0.0</precipMM><precipInches>0.0</precipInches><humidity>97</humidity><visibility>2</visibility><visibilityMiles>1</visibilityMiles><pressure>1029</pressure><pressureInches>31</pressureInches><cloudcover>24</cloudcover><HeatIndexC>-24</HeatIndexC><HeatIndexF>-11</HeatIndexF><DewPointC>-24</DewPointC><DewPointF>-11</DewPointF><WindChillC>-30</WindChillC><WindChillF>-23</WindChillF><WindGustMiles>10</WindGustMiles><WindGustKmph>16</WindGustKmph><FeelsLikeC>-30</FeelsLikeC><FeelsLikeF>-23</FeelsLikeF><uvIndex>1</uvIndex></hourly></weather></data>'