b'<?xml version="1.0" encoding="UTF-8"?><data><request><type>LatLon</type><query>Lat 25.04 and Lon 94.01</query></request><weather><date>2011-05-30</date><astronomy><sunrise>04:24 AM</sunrise><sunset>05:59 PM</sunset><moonrise>02:15 AM</moonrise><moonset>03:47 PM</moonset><moon_phase>Waning Crescent</moon_phase><moon_illumination>5</moon_illumination></astronomy><maxtempC>26</maxtempC><maxtempF>79</maxtempF><mintempC>19</mintempC><mintempF>66</mintempF><avgtempC>22</avgtempC><avgtempF>72</avgtempF><totalSnow_cm>0.0</totalSnow_cm><sunHour>9.1</sunHour><uvIndex>5</uvIndex><hourly><time>0</time><tempC>19</tempC><tempF>66</tempF><windspeedMiles>2</windspeedMiles><windspeedKmph>3</windspeedKmph><winddirDegree>228</winddirDegree><winddir16Point>SW</winddir16Point><weatherCode>299</weatherCode><weatherIconUrl><![CDATA[http://cdn.worldweatheronline.com/images/wsymbols01_png_64/wsymbol_0026_heavy_rain_showers_night.png]]></weatherIconUrl><weatherDesc><![CDATA[Moderate rain at times]]></weatherDesc><precipMM>0.9</precipMM><precipInches>0.0</precipInches><humidity>98</humidity><visibility>4</visibility><visibilityMiles>2</visibilityMiles><pressure>1005</pressure><pressureInches>30</pressureInches><cloudcover>67</cloudcover><HeatIndexC>19</HeatIndexC><HeatIndexF>67</HeatIndexF><DewPointC>19</DewPointC><DewPointF>66</DewPointF><WindChillC>19</WindChillC><WindChillF>67</WindChillF><WindGustMiles>4</WindGustMiles><WindGustKmph>6</WindGustKmph><FeelsLikeC>19</FeelsLikeC><FeelsLikeF>67</FeelsLikeF><uvIndex>1</uvIndex></hourly><hourly><time>300</time><tempC>21</tempC><tempF>69</tempF><windspeedMiles>2</windspeedMiles><windspeedKmph>3</windspeedKmph><winddirDegree>182</winddirDegree><winddir16Point>S</winddir16Point><weatherCode>299</weatherCode><weatherIconUrl><![CDATA[http://cdn.worldweatheronline.com/images/wsymbols01_png_64/wsymbol_0026_heavy_rain_showers_night.png]]></weatherIconUrl><weatherDesc><![CDATA[Moderate rain at times]]></weatherDesc><precipMM>0.6</precipMM><precipInches>0.0</precipInches><humidity>93</humidity><visibility>7</visibility><visibilityMiles>4</visibilityMiles><pressure>1006</pressure><pressureInches>30</pressureInches><cloudcover>54</cloudcover><HeatIndexC>23</HeatIndexC><HeatIndexF>73</HeatIndexF><DewPointC>20</DewPointC><DewPointF>68</DewPointF><WindChillC>21</WindChillC><WindChillF>70</WindChillF><WindGustMiles>3</WindGustMiles><WindGustKmph>4</WindGustKmph><FeelsLikeC>21</FeelsLikeC><FeelsLikeF>70</FeelsLikeF><uvIndex>1</uvIndex></hourly><hourly><time>600</time><tempC>25</tempC><tempF>77</tempF><windspeedMiles>3</windspeedMiles><windspeedKmph>5</windspeedKmph><winddirDegree>188</winddirDegree><winddir16Point>S</winddir16Point><weatherCode>299</weatherCode><weatherIconUrl><![CDATA[http://cdn.worldweatheronline.com/images/wsymbols01_png_64/wsymbol_0010_heavy_rain_showers.png]]></weatherIconUrl><weatherDesc><![CDATA[Moderate rain at times]]></weatherDesc><precipMM>0.6</precipMM><precipInches>0.0</precipInches><humidity>75</humidity><visibility>9</visibility><visibilityMiles>5</visibilityMiles><pressure>1006</pressure><pressureInches>30</pressureInches><cloudcover>76</cloudcover><HeatIndexC>27</HeatIndexC><HeatIndexF>81</HeatIndexF><DewPointC>20</DewPointC><DewPointF>68</DewPointF><WindChillC>25</WindChillC><WindChillF>78</WindChillF><WindGustMiles>4</WindGustMiles><WindGustKmph>6</WindGustKmph><FeelsLikeC>27</FeelsLikeC><FeelsLikeF>81</FeelsLikeF><uvIndex>5</uvIndex></hourly><hourly><time>900</time><tempC>26</tempC><tempF>79</tempF><windspeedMiles>3</windspeedMiles><windspeedKmph>4</windspeedKmph><winddirDegree>178</winddirDegree><winddir16Point>S</winddir16Point><weatherCode>116</weatherCode><weatherIconUrl><![CDATA[http://cdn.worldweatheronline.com/images/wsymbols01_png_64/wsymbol_0002_sunny_intervals.png]]></weatherIconUrl><weatherDesc><![CDATA[Partly cloudy]]></weatherDesc><precipMM>0.0</precipMM><precipInches>0.0</precipInches><humidity>73</humidity><visibility>9</visibility><visibilityMiles>5</visibilityMiles><pressure>1004</pressure><pressureInches>30</pressureInches><cloudcover>46</cloudcover><HeatIndexC>29</HeatIndexC><HeatIndexF>84</HeatIndexF><DewPointC>21</DewPointC><DewPointF>70</DewPointF><WindChillC>27</WindChillC><WindChillF>80</WindChillF><WindGustMiles>3</WindGustMiles><WindGustKmph>5</WindGustKmph><FeelsLikeC>29</FeelsLikeC><FeelsLikeF>84</FeelsLikeF><uvIndex>7</uvIndex></hourly><hourly><time>1200</time><tempC>26</tempC><tempF>79</tempF><windspeedMiles>4</windspeedMiles><windspeedKmph>7</windspeedKmph><winddirDegree>202</winddirDegree><winddir16Point>SSW</winddir16Point><weatherCode>356</weatherCode><weatherIconUrl><![CDATA[http://cdn.worldweatheronline.com/images/wsymbols01_png_64/wsymbol_0010_heavy_rain_showers.png]]></weatherIconUrl><weatherDesc><![CDATA[Moderate or heavy rain shower]]></weatherDesc><precipMM>3.3</precipMM><precipInches>0.1</precipInches><humidity>75</humidity><visibility>8</visibility><visibilityMiles>5</visibilityMiles><pressure>1002</pressure><pressureInches>30</pressureInches><cloudcover>79</cloudcover><HeatIndexC>28</HeatIndexC><HeatIndexF>83</HeatIndexF><DewPointC>21</DewPointC><DewPointF>70</DewPointF><WindChillC>26</WindChillC><WindChillF>79</WindChillF><WindGustMiles>6</WindGustMiles><WindGustKmph>10</WindGustKmph><FeelsLikeC>28</FeelsLikeC><FeelsLikeF>83</FeelsLikeF><uvIndex>6</uvIndex></hourly><hourly><time>1500</time><tempC>22</tempC><tempF>72</tempF><windspeedMiles>3</windspeedMiles><windspeedKmph>4</windspeedKmph><winddirDegree>216</winddirDegree><winddir16Point>SW</winddir16Point><weatherCode>119</weatherCode><weatherIconUrl><![CDATA[http://cdn.worldweatheronline.com/images/wsymbols01_png_64/wsymbol_0003_white_cloud.png]]></weatherIconUrl><weatherDesc><![CDATA[Cloudy]]></weatherDesc><precipMM>0.0</precipMM><precipInches>0.0</precipInches><humidity>89</humidity><visibility>6</visibility><visibilityMiles>3</visibilityMiles><pressure>1003</pressure><pressureInches>30</pressureInches><cloudcover>53</cloudcover><HeatIndexC>25</HeatIndexC><HeatIndexF>77</HeatIndexF><DewPointC>21</DewPointC><DewPointF>70</DewPointF><WindChillC>23</WindChillC><WindChillF>73</WindChillF><WindGustMiles>4</WindGustMiles><WindGustKmph>7</WindGustKmph><FeelsLikeC>25</FeelsLikeC><FeelsLikeF>77</FeelsLikeF><uvIndex>5</uvIndex></hourly><hourly><time>1800</time><tempC>20</tempC><tempF>68</tempF><windspeedMiles>2</windspeedMiles><windspeedKmph>4</windspeedKmph><winddirDegree>217</winddirDegree><winddir16Point>SW</winddir16Point><weatherCode>356</weatherCode><weatherIconUrl><![CDATA[http://cdn.worldweatheronline.com/images/wsymbols01_png_64/wsymbol_0026_heavy_rain_showers_night.png]]></weatherIconUrl><weatherDesc><![CDATA[Moderate or heavy rain shower]]></weatherDesc><precipMM>2.9</precipMM><precipInches>0.1</precipInches><humidity>97</humidity><visibility>6</visibility><visibilityMiles>3</visibilityMiles><pressure>1005</pressure><pressureInches>30</pressureInches><cloudcover>57</cloudcover><HeatIndexC>21</HeatIndexC><HeatIndexF>70</HeatIndexF><DewPointC>20</DewPointC><DewPointF>68</DewPointF><WindChillC>21</WindChillC><WindChillF>69</WindChillF><WindGustMiles>4</WindGustMiles><WindGustKmph>6</WindGustKmph><FeelsLikeC>21</FeelsLikeC><FeelsLikeF>69</FeelsLikeF><uvIndex>1</uvIndex></hourly><hourly><time>2100</time><tempC>19</tempC><tempF>66</tempF><windspeedMiles>2</windspeedMiles><windspeedKmph>3</windspeedKmph><winddirDegree>180</winddirDegree><winddir16Point>S</winddir16Point><weatherCode>119</weatherCode><weatherIconUrl><![CDATA[http://cdn.worldweatheronline.com/images/wsymbols01_png_64/wsymbol_0003_white_cloud.png]]></weatherIconUrl><weatherDesc><![CDATA[Cloudy]]></weatherDesc><precipMM>0.0</precipMM><precipInches>0.0</precipInches><humidity>98</humidity><visibility>2</visibility><visibilityMiles>0</visibilityMiles><pressure>1006</pressure><pressureInches>30</pressureInches><cloudcover>69</cloudcover><HeatIndexC>19</HeatIndexC><HeatIndexF>67</HeatIndexF><DewPointC>19</DewPointC><DewPointF>66</DewPointF><WindChillC>19</WindChillC><WindChillF>67</WindChillF><WindGustMiles>3</WindGustMiles><WindGustKmph>5</WindGustKmph><FeelsLikeC>19</FeelsLikeC><FeelsLikeF>67</FeelsLikeF><uvIndex>1</uvIndex></hourly></weather></data>'