b'<?xml version="1.0" encoding="UTF-8"?><data><request><type>LatLon</type><query>Lat 31.00 and Lon 78.94</query></request><weather><date>2016-08-28</date><astronomy><sunrise>05:48 AM</sunrise><sunset>06:42 PM</sunset><moonrise>01:44 AM</moonrise><moonset>03:45 PM</moonset><moon_phase>Waning Crescent</moon_phase><moon_illumination>23</moon_illumination></astronomy><maxtempC>18</maxtempC><maxtempF>65</maxtempF><mintempC>5</mintempC><mintempF>42</mintempF><avgtempC>12</avgtempC><avgtempF>53</avgtempF><totalSnow_cm>0.0</totalSnow_cm><sunHour>12.9</sunHour><uvIndex>4</uvIndex><hourly><time>0</time><tempC>6</tempC><tempF>43</tempF><windspeedMiles>1</windspeedMiles><windspeedKmph>2</windspeedKmph><winddirDegree>300</winddirDegree><winddir16Point>WNW</winddir16Point><weatherCode>113</weatherCode><weatherIconUrl><![CDATA[http://cdn.worldweatheronline.com/images/wsymbols01_png_64/wsymbol_0008_clear_sky_night.png]]></weatherIconUrl><weatherDesc><![CDATA[Clear]]></weatherDesc><precipMM>0.0</precipMM><precipInches>0.0</precipInches><humidity>88</humidity><visibility>10</visibility><visibilityMiles>6</visibilityMiles><pressure>1016</pressure><pressureInches>30</pressureInches><cloudcover>16</cloudcover><HeatIndexC>6</HeatIndexC><HeatIndexF>43</HeatIndexF><DewPointC>4</DewPointC><DewPointF>40</DewPointF><WindChillC>6</WindChillC><WindChillF>43</WindChillF><WindGustMiles>3</WindGustMiles><WindGustKmph>5</WindGustKmph><FeelsLikeC>6</FeelsLikeC><FeelsLikeF>43</FeelsLikeF><uvIndex>1</uvIndex></hourly><hourly><time>300</time><tempC>5</tempC><tempF>42</tempF><windspeedMiles>1</windspeedMiles><windspeedKmph>2</windspeedKmph><winddirDegree>300</winddirDegree><winddir16Point>WNW</winddir16Point><weatherCode>113</weatherCode><weatherIconUrl><![CDATA[http://cdn.worldweatheronline.com/images/wsymbols01_png_64/wsymbol_0008_clear_sky_night.png]]></weatherIconUrl><weatherDesc><![CDATA[Clear]]></weatherDesc><precipMM>0.0</precipMM><precipInches>0.0</precipInches><humidity>86</humidity><visibility>10</visibility><visibilityMiles>6</visibilityMiles><pressure>1017</pressure><pressureInches>31</pressureInches><cloudcover>13</cloudcover><HeatIndexC>5</HeatIndexC><HeatIndexF>42</HeatIndexF><DewPointC>3</DewPointC><DewPointF>38</DewPointF><WindChillC>5</WindChillC><WindChillF>42</WindChillF><WindGustMiles>3</WindGustMiles><WindGustKmph>5</WindGustKmph><FeelsLikeC>5</FeelsLikeC><FeelsLikeF>42</FeelsLikeF><uvIndex>1</uvIndex></hourly><hourly><time>600</time><tempC>15</tempC><tempF>59</tempF><windspeedMiles>4</windspeedMiles><windspeedKmph>7</windspeedKmph><winddirDegree>227</winddirDegree><winddir16Point>SW</winddir16Point><weatherCode>113</weatherCode><weatherIconUrl><![CDATA[http://cdn.worldweatheronline.com/images/wsymbols01_png_64/wsymbol_0001_sunny.png]]></weatherIconUrl><weatherDesc><![CDATA[Sunny]]></weatherDesc><precipMM>0.0</precipMM><precipInches>0.0</precipInches><humidity>47</humidity><visibility>10</visibility><visibilityMiles>6</visibilityMiles><pressure>1017</pressure><pressureInches>31</pressureInches><cloudcover>8</cloudcover><HeatIndexC>15</HeatIndexC><HeatIndexF>59</HeatIndexF><DewPointC>4</DewPointC><DewPointF>39</DewPointF><WindChillC>15</WindChillC><WindChillF>59</WindChillF><WindGustMiles>5</WindGustMiles><WindGustKmph>8</WindGustKmph><FeelsLikeC>15</FeelsLikeC><FeelsLikeF>59</FeelsLikeF><uvIndex>5</uvIndex></hourly><hourly><time>900</time><tempC>18</tempC><tempF>65</tempF><windspeedMiles>7</windspeedMiles><windspeedKmph>11</windspeedKmph><winddirDegree>225</winddirDegree><winddir16Point>SW</winddir16Point><weatherCode>113</weatherCode><weatherIconUrl><![CDATA[http://cdn.worldweatheronline.com/images/wsymbols01_png_64/wsymbol_0001_sunny.png]]></weatherIconUrl><weatherDesc><![CDATA[Sunny]]></weatherDesc><precipMM>0.0</precipMM><precipInches>0.0</precipInches><humidity>40</humidity><visibility>10</visibility><visibilityMiles>6</visibilityMiles><pressure>1016</pressure><pressureInches>30</pressureInches><cloudcover>10</cloudcover><HeatIndexC>18</HeatIndexC><HeatIndexF>65</HeatIndexF><DewPointC>5</DewPointC><DewPointF>40</DewPointF><WindChillC>18</WindChillC><WindChillF>65</WindChillF><WindGustMiles>8</WindGustMiles><WindGustKmph>13</WindGustKmph><FeelsLikeC>18</FeelsLikeC><FeelsLikeF>65</FeelsLikeF><uvIndex>5</uvIndex></hourly><hourly><time>1200</time><tempC>18</tempC><tempF>65</tempF><windspeedMiles>7</windspeedMiles><windspeedKmph>12</windspeedKmph><winddirDegree>225</winddirDegree><winddir16Point>SW</winddir16Point><weatherCode>113</weatherCode><weatherIconUrl><![CDATA[http://cdn.worldweatheronline.com/images/wsymbols01_png_64/wsymbol_0001_sunny.png]]></weatherIconUrl><weatherDesc><![CDATA[Sunny]]></weatherDesc><precipMM>0.4</precipMM><precipInches>0.0</precipInches><humidity>42</humidity><visibility>10</visibility><visibilityMiles>6</visibilityMiles><pressure>1013</pressure><pressureInches>30</pressureInches><cloudcover>6</cloudcover><HeatIndexC>19</HeatIndexC><HeatIndexF>65</HeatIndexF><DewPointC>5</DewPointC><DewPointF>41</DewPointF><WindChillC>19</WindChillC><WindChillF>65</WindChillF><WindGustMiles>9</WindGustMiles><WindGustKmph>14</WindGustKmph><FeelsLikeC>19</FeelsLikeC><FeelsLikeF>65</FeelsLikeF><uvIndex>5</uvIndex></hourly><hourly><time>1500</time><tempC>15</tempC><tempF>59</tempF><windspeedMiles>5</windspeedMiles><windspeedKmph>9</windspeedKmph><winddirDegree>228</winddirDegree><winddir16Point>SW</winddir16Point><weatherCode>113</weatherCode><weatherIconUrl><![CDATA[http://cdn.worldweatheronline.com/images/wsymbols01_png_64/wsymbol_0001_sunny.png]]></weatherIconUrl><weatherDesc><![CDATA[Sunny]]></weatherDesc><precipMM>0.0</precipMM><precipInches>0.0</precipInches><humidity>54</humidity><visibility>10</visibility><visibilityMiles>6</visibilityMiles><pressure>1013</pressure><pressureInches>30</pressureInches><cloudcover>6</cloudcover><HeatIndexC>15</HeatIndexC><HeatIndexF>59</HeatIndexF><DewPointC>6</DewPointC><DewPointF>43</DewPointF><WindChillC>15</WindChillC><WindChillF>59</WindChillF><WindGustMiles>7</WindGustMiles><WindGustKmph>11</WindGustKmph><FeelsLikeC>15</FeelsLikeC><FeelsLikeF>59</FeelsLikeF><uvIndex>5</uvIndex></hourly><hourly><time>1800</time><tempC>7</tempC><tempF>45</tempF><windspeedMiles>1</windspeedMiles><windspeedKmph>1</windspeedKmph><winddirDegree>6</winddirDegree><winddir16Point>N</winddir16Point><weatherCode>113</weatherCode><weatherIconUrl><![CDATA[http://cdn.worldweatheronline.com/images/wsymbols01_png_64/wsymbol_0008_clear_sky_night.png]]></weatherIconUrl><weatherDesc><![CDATA[Clear]]></weatherDesc><precipMM>0.0</precipMM><precipInches>0.0</precipInches><humidity>86</humidity><visibility>10</visibility><visibilityMiles>6</visibilityMiles><pressure>1015</pressure><pressureInches>30</pressureInches><cloudcover>5</cloudcover><HeatIndexC>8</HeatIndexC><HeatIndexF>46</HeatIndexF><DewPointC>5</DewPointC><DewPointF>42</DewPointF><WindChillC>8</WindChillC><WindChillF>46</WindChillF><WindGustMiles>2</WindGustMiles><WindGustKmph>3</WindGustKmph><FeelsLikeC>8</FeelsLikeC><FeelsLikeF>46</FeelsLikeF><uvIndex>1</uvIndex></hourly><hourly><time>2100</time><tempC>6</tempC><tempF>43</tempF><windspeedMiles>1</windspeedMiles><windspeedKmph>1</windspeedKmph><winddirDegree>291</winddirDegree><winddir16Point>WNW</winddir16Point><weatherCode>113</weatherCode><weatherIconUrl><![CDATA[http://cdn.worldweatheronline.com/images/wsymbols01_png_64/wsymbol_0008_clear_sky_night.png]]></weatherIconUrl><weatherDesc><![CDATA[Clear]]></weatherDesc><precipMM>0.0</precipMM><precipInches>0.0</precipInches><humidity>86</humidity><visibility>10</visibility><visibilityMiles>6</visibilityMiles><pressure>1016</pressure><pressureInches>30</pressureInches><cloudcover>5</cloudcover><HeatIndexC>6</HeatIndexC><HeatIndexF>43</HeatIndexF><DewPointC>4</DewPointC><DewPointF>39</DewPointF><WindChillC>6</WindChillC><WindChillF>43</WindChillF><WindGustMiles>2</WindGustMiles><WindGustKmph>3</WindGustKmph><FeelsLikeC>6</FeelsLikeC><FeelsLikeF>43</FeelsLikeF><uvIndex>1</uvIndex></hourly></weather></data>'